{
	"backtrace" : 5,
	"backtraceGraph" : 
	{
		"commands" : 
		[
			"add_custom_target",
			"include",
			"generate_messages",
			"catkin_simple",
			"add_dependencies"
		],
		"files" : 
		[
			"cmake-build-debug/sort_ros/cmake/sort_ros-genmsg.cmake",
			"/opt/ros/melodic/share/genmsg/cmake/genmsg-extras.cmake",
			"cmake-build-debug/devel/share/catkin_simple/cmake/catkin_simple-extras.cmake",
			"sort_ros/CMakeLists.txt"
		],
		"nodes" : 
		[
			{
				"file" : 3
			},
			{
				"command" : 3,
				"file" : 3,
				"line" : 19,
				"parent" : 0
			},
			{
				"command" : 2,
				"file" : 2,
				"line" : 102,
				"parent" : 1
			},
			{
				"command" : 1,
				"file" : 1,
				"line" : 307,
				"parent" : 2
			},
			{
				"file" : 0,
				"parent" : 3
			},
			{
				"command" : 0,
				"file" : 0,
				"line" : 221,
				"parent" : 4
			},
			{
				"command" : 4,
				"file" : 0,
				"line" : 396,
				"parent" : 4
			},
			{
				"command" : 4,
				"file" : 0,
				"line" : 399,
				"parent" : 4
			},
			{
				"command" : 4,
				"file" : 0,
				"line" : 402,
				"parent" : 4
			},
			{
				"command" : 4,
				"file" : 0,
				"line" : 411,
				"parent" : 4
			},
			{
				"command" : 4,
				"file" : 0,
				"line" : 390,
				"parent" : 4
			},
			{
				"command" : 4,
				"file" : 0,
				"line" : 414,
				"parent" : 4
			},
			{
				"command" : 4,
				"file" : 0,
				"line" : 393,
				"parent" : 4
			},
			{
				"command" : 4,
				"file" : 0,
				"line" : 405,
				"parent" : 4
			},
			{
				"command" : 4,
				"file" : 0,
				"line" : 408,
				"parent" : 4
			},
			{
				"command" : 4,
				"file" : 0,
				"line" : 228,
				"parent" : 4
			},
			{
				"command" : 4,
				"file" : 0,
				"line" : 230,
				"parent" : 4
			}
		]
	},
	"dependencies" : 
	[
		{
			"backtrace" : 6,
			"id" : "std_msgs_generate_messages_py::@efc7306d6d373c619d47"
		},
		{
			"backtrace" : 7,
			"id" : "geometry_msgs_generate_messages_py::@efc7306d6d373c619d47"
		},
		{
			"backtrace" : 8,
			"id" : "sensor_msgs_generate_messages_py::@9f568450e6e9336c6f3a"
		},
		{
			"backtrace" : 9,
			"id" : "darknet_ros_msgs_generate_messages_py::@9f568450e6e9336c6f3a"
		},
		{
			"backtrace" : 10,
			"id" : "roscpp_generate_messages_py::@91b5af77f4f4499c4261"
		},
		{
			"backtrace" : 11,
			"id" : "nodelet_generate_messages_py::@91b5af77f4f4499c4261"
		},
		{
			"backtrace" : 12,
			"id" : "tf_generate_messages_py::@7b88bf5e6409a72d3681"
		},
		{
			"backtrace" : 13,
			"id" : "nav_msgs_generate_messages_py::@7b88bf5e6409a72d3681"
		},
		{
			"backtrace" : 14,
			"id" : "visualization_msgs_generate_messages_py::@7b88bf5e6409a72d3681"
		},
		{
			"backtrace" : 15,
			"id" : "_sort_ros_generate_messages_check_deps_TrackedBoundingBox::@7b88bf5e6409a72d3681"
		},
		{
			"backtrace" : 16,
			"id" : "_sort_ros_generate_messages_check_deps_TrackedBoundingBoxes::@7b88bf5e6409a72d3681"
		}
	],
	"id" : "sort_ros_generate_messages_py::@7b88bf5e6409a72d3681",
	"name" : "sort_ros_generate_messages_py",
	"paths" : 
	{
		"build" : "sort_ros",
		"source" : "sort_ros"
	},
	"sourceGroups" : 
	[
		{
			"name" : "",
			"sourceIndexes" : 
			[
				0
			]
		},
		{
			"name" : "CMake Rules",
			"sourceIndexes" : 
			[
				1,
				2,
				3,
				4
			]
		}
	],
	"sources" : 
	[
		{
			"backtrace" : 5,
			"isGenerated" : true,
			"path" : "cmake-build-debug/sort_ros/CMakeFiles/sort_ros_generate_messages_py",
			"sourceGroupIndex" : 0
		},
		{
			"backtrace" : 0,
			"isGenerated" : true,
			"path" : "cmake-build-debug/sort_ros/CMakeFiles/sort_ros_generate_messages_py.rule",
			"sourceGroupIndex" : 1
		},
		{
			"backtrace" : 0,
			"isGenerated" : true,
			"path" : "cmake-build-debug/devel/lib/python2.7/dist-packages/sort_ros/msg/_TrackedBoundingBox.py.rule",
			"sourceGroupIndex" : 1
		},
		{
			"backtrace" : 0,
			"isGenerated" : true,
			"path" : "cmake-build-debug/devel/lib/python2.7/dist-packages/sort_ros/msg/_TrackedBoundingBoxes.py.rule",
			"sourceGroupIndex" : 1
		},
		{
			"backtrace" : 0,
			"isGenerated" : true,
			"path" : "cmake-build-debug/devel/lib/python2.7/dist-packages/sort_ros/msg/__init__.py.rule",
			"sourceGroupIndex" : 1
		}
	],
	"type" : "UTILITY"
}
